{
  "statistical_data": {
    "friends_num": 2,
    "active_num": 2,
    "error_num": 0,
    "article_num": 10,
    "last_updated_time": "2025-10-19 00:02:50"
  },
  "article_data": [
    {
      "title": "Week Ending October 12, 2025",
      "created": "2025-10-16 06:00",
      "link": "https://lwkd.info/2025/20251015",
      "author": "LWKD",
      "avatar": "https://lwkd.info/images/logo.png"
    },
    {
      "title": "Week Ending October 5, 2025",
      "created": "2025-10-10 21:03",
      "link": "https://lwkd.info/2025/20251010",
      "author": "LWKD",
      "avatar": "https://lwkd.info/images/logo.png"
    },
    {
      "title": "使用TinyAuth实现任意应用登录认证",
      "created": "2025-10-07 16:20",
      "link": "https://blog.liushen.fun/posts/362bfd8b/",
      "author": "清羽飞扬",
      "avatar": "https://blog.liushen.fun/info/avatar.ico"
    },
    {
      "title": "Week Ending September 28, 2025",
      "created": "2025-10-02 18:25",
      "link": "https://lwkd.info/2025/20251002",
      "author": "LWKD",
      "avatar": "https://lwkd.info/images/logo.png"
    },
    {
      "title": "不同姿势部署Anheyu-App应用",
      "created": "2025-09-30 23:59",
      "link": "https://blog.liushen.fun/posts/e3f6f966/",
      "author": "清羽飞扬",
      "avatar": "https://blog.liushen.fun/info/avatar.ico"
    },
    {
      "title": "Week Ending September 21, 2025",
      "created": "2025-09-26 07:19",
      "link": "https://lwkd.info/2025/20250925",
      "author": "LWKD",
      "avatar": "https://lwkd.info/images/logo.png"
    },
    {
      "title": "Week Ending September 14, 2025",
      "created": "2025-09-19 05:00",
      "link": "https://lwkd.info/2025/20250918",
      "author": "LWKD",
      "avatar": "https://lwkd.info/images/logo.png"
    },
    {
      "title": "Casdoor强行兼容Artalk社交登录",
      "created": "2025-09-16 23:50",
      "link": "https://blog.liushen.fun/posts/8624756e/",
      "author": "清羽飞扬",
      "avatar": "https://blog.liushen.fun/info/avatar.ico"
    },
    {
      "title": "血证未泯，山河已立",
      "created": "2025-09-09 13:50",
      "link": "https://blog.liushen.fun/posts/886ab86a/",
      "author": "清羽飞扬",
      "avatar": "https://blog.liushen.fun/info/avatar.ico"
    },
    {
      "title": "第三方1Panel应用商店不完全指北",
      "created": "2025-08-29 15:50",
      "link": "https://blog.liushen.fun/posts/470abaf8/",
      "author": "清羽飞扬",
      "avatar": "https://blog.liushen.fun/info/avatar.ico"
    }
  ]
}